{
    "data":  {
                 "mitre_attack_techniques":  [
                                                 {
                                                     "id":  "T1082",
                                                     "severity":  "IMPACT_SEVERITY_INFO",
                                                     "signature_description":  "query environment variable",
                                                     "refs":  [
                                                                  {
                                                                      "ref":  "#signature_matches",
                                                                      "value":  "0"
                                                                  }
                                                              ]
                                                 }
                                             ],
                 "signature_matches":  [
                                           {
                                               "id":  "0",
                                               "format":  "SIG_FORMAT_CAPA",
                                               "name":  "query environment variable",
                                               "description":  "host-interaction/environment-variable",
                                               "authors":  [
                                                               "michael.hunhoff@mandiant.com",
                                                               "@_re_fox"
                                                           ],
                                               "match_data":  [
                                                                  "api: getenv"
                                                              ],
                                               "rule_src":  "rule:\n  meta:\n    name: query environment variable\n    namespace: host-interaction/environment-variable\n    authors:\n      - michael.hunhoff@mandiant.com\n      - \"@_re_fox\"\n    scopes:\n      static: function\n      dynamic: call\n    att\u0026ck:\n      - Discovery::System Information Discovery [T1082]\n    mbc:\n      - Discovery::System Information Discovery [E1082]\n    examples:\n      - Practical Malware Analysis Lab 14-02.exe_:0x401880\n      - 0761142efbda6c4b1e801223de723578:0x65483490\n  features:\n    - or:\n      - api: kernel32.GetEnvironmentVariable\n      - api: kernel32.GetEnvironmentStrings\n      - api: kernel32.ExpandEnvironmentStrings\n      - api: msvcr90.getenv\n      - api: msvcrt.getenv\n      - api: System.Environment::GetEnvironmentVariable\n      - api: System.Environment::GetEnvironmentVariables\n      - api: System.Environment::ExpandEnvironmentVariables\n"
                                           }
                                       ],
                 "mbc":  [
                             {
                                 "id":  "E1082",
                                 "objective":  "Discovery",
                                 "behavior":  "System Information Discovery",
                                 "refs":  [
                                              {
                                                  "ref":  "#signature_matches",
                                                  "value":  "0"
                                              }
                                          ]
                             }
                         ],
                 "attack_techniques":  {
                                           "T1082":  [
                                                         {
                                                             "severity":  "INFO",
                                                             "description":  "query environment variable",
                                                             "refs":  [
                                                                          {
                                                                              "ref":  "#signature_matches",
                                                                              "value":  "0"
                                                                          }
                                                                      ]
                                                         }
                                                     ]
                                       }
             }
}
