{
    "data":  {
                 "signature_matches":  [
                                           {
                                               "id":  "1",
                                               "format":  "SIG_FORMAT_CAPA",
                                               "name":  "hash data using djb2",
                                               "description":  "data-manipulation/hashing/djb2",
                                               "authors":  [
                                                               "awillia2@cisco.com",
                                                               "still@teamt5.org"
                                                           ],
                                               "match_data":  [
                                                                  "mnemonic: mov",
                                                                  "mnemonic: shl"
                                                              ],
                                               "rule_src":  "rule:\n  meta:\n    name: hash data using djb2\n    namespace: data-manipulation/hashing/djb2\n    authors:\n      - awillia2@cisco.com\n      - still@teamt5.org\n    scopes:\n      static: function\n      dynamic: unsupported  # requires mnemonic features\n    mbc:\n      - Data::Non-Cryptographic Hash::djb2 [C0030.006]\n    references:\n      - https://twitter.com/r3c0nst/status/1392405576131436546\n      - http://www.cse.yorku.ca/~oz/hash.html\n    examples:\n      - 6be0ae5cb7c3155f70d608fc7670d2d9:0x41DD19\n  features:\n    - and:\n      - instruction:\n        - description: hash = 5381\n        - mnemonic: mov\n        - number: 5381\n      - or:\n        - instruction:\n          - description: hash \u003c\u003c 5\n          - mnemonic: shl\n          - number: 5\n        - instruction:\n          - description: hash * 33\n          - or:\n            - mnemonic: mul\n            - mnemonic: imul\n          - number: 33\n",
                                               "refs":  [
                                                            {
                                                                "ref":  "https://twitter.com/r3c0nst/status/1392405576131436546"
                                                            },
                                                            {
                                                                "ref":  "http://www.cse.yorku.ca/~oz/hash.html"
                                                            }
                                                        ]
                                           }
                                       ],
                 "mbc":  [
                             {
                                 "id":  "C0030.006",
                                 "objective":  "Data",
                                 "behavior":  "Non-Cryptographic Hash",
                                 "method":  "djb2",
                                 "refs":  [
                                              {
                                                  "ref":  "#signature_matches",
                                                  "value":  "1"
                                              }
                                          ]
                             }
                         ]
             }
}
