{
    "data":  {
                 "signature_matches":  [
                                           {
                                               "id":  "1",
                                               "format":  "SIG_FORMAT_CAPA",
                                               "name":  "packed with UPX",
                                               "description":  "anti-analysis/packer/upx",
                                               "authors":  [
                                                               "william.ballenthin@mandiant.com"
                                                           ],
                                               "match_data":  [
                                                                  "section: UPX0",
                                                                  "section: UPX1"
                                                              ],
                                               "rule_src":  "rule:\n  meta:\n    name: packed with UPX\n    namespace: anti-analysis/packer/upx\n    authors:\n      - william.ballenthin@mandiant.com\n    scopes:\n      static: file\n      dynamic: file\n    att\u0026ck:\n      - Defense Evasion::Obfuscated Files or Information::Software Packing [T1027.002]\n    mbc:\n      - Anti-Static Analysis::Software Packing::UPX [F0001.008]\n    examples:\n      - CD2CBA9E6313E8DF2C1273593E649682\n      - Practical Malware Analysis Lab 01-02.exe_:0x0401000\n  features:\n    - or:\n      - and:\n        - format: pe\n        - or:\n          - section: UPX0\n          - section: UPX1\n      - and:\n        - format: elf\n        - or:\n          - string: \"UPX!\"\n"
                                           }
                                       ],
                 "mbc":  [
                             {
                                 "id":  "F0001.008",
                                 "objective":  "Anti-Static Analysis",
                                 "behavior":  "Software Packing",
                                 "method":  "UPX",
                                 "refs":  [
                                              {
                                                  "ref":  "#signature_matches",
                                                  "value":  "1"
                                              }
                                          ]
                             }
                         ],
                 "mitre_attack_techniques":  [
                                                 {
                                                     "id":  "T1027.002",
                                                     "severity":  "IMPACT_SEVERITY_INFO",
                                                     "signature_description":  "packed with UPX",
                                                     "refs":  [
                                                                  {
                                                                      "ref":  "#signature_matches",
                                                                      "value":  "1"
                                                                  }
                                                              ]
                                                 }
                                             ],
                 "attack_techniques":  {
                                           "T1027.002":  [
                                                             {
                                                                 "severity":  "INFO",
                                                                 "description":  "packed with UPX",
                                                                 "refs":  [
                                                                              {
                                                                                  "ref":  "#signature_matches",
                                                                                  "value":  "1"
                                                                              }
                                                                          ]
                                                             }
                                                         ]
                                       }
             }
}
